CHANGELOG
LICENSE
MANIFEST.in
README.rst
distribute_setup.py
setup.py
docs/Makefile
docs/source/api.rst
docs/source/command.rst
docs/source/conf.py
docs/source/guide.rst
docs/source/guide_content
docs/source/index.rst
docs/source/_templates/page.html
filemagic.egg-info/PKG-INFO
filemagic.egg-info/SOURCES.txt
filemagic.egg-info/dependency_links.txt
filemagic.egg-info/not-zip-safe
filemagic.egg-info/top_level.txt
magic/__init__.py
magic/api.py
magic/command.py
magic/compatability.py
magic/flags.py
magic/identify.py
magic/version.py
tests/__init__.py
tests/test_magic.py